InterfaceForLabs/__init__.py
InterfaceForLabs/interface.py
InterfaceForLabs-0.0.1.dist-info/LICENSE
InterfaceForLabs-0.0.1.dist-info/METADATA
InterfaceForLabs-0.0.1.dist-info/WHEEL
InterfaceForLabs-0.0.1.dist-info/top_level.txt
InterfaceForLabs-0.0.1.dist-info/RECORD
